yproject/__init__.py
yproject/y.py
yproject-1.0.2.dist-info/LICENSE
yproject-1.0.2.dist-info/METADATA
yproject-1.0.2.dist-info/WHEEL
yproject-1.0.2.dist-info/top_level.txt
yproject-1.0.2.dist-info/RECORD
