Metadata-Version: 2.1
Name: yproject
Version: 1.0.2
Summary: Pipes for humans.
Author-email: Ben Karcher <s6bkarc@uni-bonn.de>, wbrandon@csail.mit.edu, bdrisc@cs.stanford.edu, fydai@berkeley.edu, Lukas Sabatschus <lus@wallpen.com>, Ethan Smith <ethan@python.org>
Project-URL: Homepage, https://y-project.dev
Project-URL: Issues, https://github.com/the-y-project/y/issues
License-File: LICENSE
